objectify/__init__.py
objectify/converter.py
objectify-1.1.0.dist-info/METADATA
objectify-1.1.0.dist-info/WHEEL
objectify-1.1.0.dist-info/licenses/LICENSE
objectify-1.1.0.dist-info/RECORD
