Metadata-Version: 2.4
Name: objectify
Version: 1.1.0
Summary: A package to convert a dictionary to an object to achieve similar syntax and auto-completion as in TypeScript when annotating objects with interfaces.
Project-URL: Homepage, https://github.com/anviks/objectify
Project-URL: Issues, https://github.com/anviks/objectify/issues
Project-URL: Changelog, https://github.com/anviks/objectify/blob/main/CHANGELOG.md
Author-email: Andreas Marten Viks <andreasviks1@gmail.com>
License-File: LICENSE
Classifier: License :: OSI Approved :: MIT License
Classifier: Operating System :: OS Independent
Classifier: Programming Language :: Python :: 3
Requires-Python: >=3.10
Provides-Extra: dev
Requires-Dist: pytest; extra == 'dev'
